gerapy_rabbitmq/__init__.py
gerapy_rabbitmq/__version__.py
gerapy_rabbitmq/connection.py
gerapy_rabbitmq/defaults.py
gerapy_rabbitmq/queue.py
gerapy_rabbitmq/scheduler.py
gerapy_rabbitmq-0.1.1.dist-info/METADATA
gerapy_rabbitmq-0.1.1.dist-info/WHEEL
gerapy_rabbitmq-0.1.1.dist-info/top_level.txt
gerapy_rabbitmq-0.1.1.dist-info/RECORD
